pywdl/__init__.py
pywdl/exceptions.py
pywdl/hooks.py
pywdl/models.py
pywdl/transforms.py
pywdl/types.py
pywdl/utils.py
pywdl/antlr/WdlLexer.py
pywdl/antlr/WdlParser.py
pywdl/antlr/WdlParserListener.py
pywdl/antlr/WdlParserVisitor.py
pywdl/antlr/__init__.py
pywdl-0.0.1.dist-info/METADATA
pywdl-0.0.1.dist-info/WHEEL
pywdl-0.0.1.dist-info/top_level.txt
pywdl-0.0.1.dist-info/RECORD
