Metadata-Version: 2.1
Name: pywdl
Version: 0.0.1
Summary: UNKNOWN
Home-page: UNKNOWN
Author: UNKNOWN
Author-email: UNKNOWN
License: UNKNOWN
Platform: UNKNOWN
Requires-Dist: antlr4-python3-runtime (==4.8)
